{
  "bg": "https://nextjs-alura-quiz.vercel.app/bg.jpg",
  "title": "Conhece o Mario?",
  "description": "Teste seu conhecimentos",
  "questions": [
    {
      "image": "https://nextjs-alura-quiz.vercel.app/img1.jpg",
      "title": "Qual personagem foi substituído por Mario em seu primeiro jogo?",
      "description": "Donkey Kong (1981)",
      "answer": 2,
      "alternatives": [
        "Toad",
        "Kirby",
        "Popeye",
        "Mickey"
      ]
    },
    {
      "image": "https://media.giphy.com/media/ksjCMQutSkK50WUPhx/giphy.gif",
      "title": "Com qual parte do corpo Mario quebra tijolos e bônus?",
      "description": "Mario cabeça dura?",
      "answer": 1,
      "alternatives": [
         "Com o ''bigodon''",
         "Com a mão",
         "Com a Cabeça"
      ]
    },
    {
      "image": "https://media.giphy.com/media/1iTX8iA3RZ9YTWuI/giphy.gif",
      "title": "Qual foi o primeiro nome do Mario?",
      "description": "Donkey Kong (1981)",
      "answer": 1,
      "alternatives": [
         "Super Plumber",
         "Jumpman"
      ]
    },
    {
      "image": "https://media.giphy.com/media/3o6fJ42Ud1rylg4eTS/giphy.gif",
      "title": "Quem foi o primeiro interesse amoroso do Mario?",
      "description": "Donkey Kong (1981)",
      "answer": 2,
      "alternatives": [
         "Olivia Palito",
         "Peach",
         "Pauline"
      ]
    }
  ],

  "external": [
    "https://aluraquiz-css.omariosouto.vercel.app/",
    "https://aluraquiz-devsoutinho.omariosouto.vercel.app/"
  ],
  "theme": {
    "colors": {
      "primary": "#711111",
      "secondary": "#29b6f6",
      "mainBg": "#2f1307",
      "contrastText": "#FFFBFF",
      "wrong": "#b74d1e",
      "success": "#4CAF50"
    },
    "borderRadius": "4px"
  }
}
